pypigeonhole_config/__init__.py
pypigeonhole_config/app_setup.py
pypigeonhole_config/ioc_conf.py
pypigeonhole_config/ioc_container.py
pypigeonhole_config/ioc_context.py
pypigeonhole_config-0.0.3.dist-info/LICENSE.md
pypigeonhole_config-0.0.3.dist-info/METADATA
pypigeonhole_config-0.0.3.dist-info/WHEEL
pypigeonhole_config-0.0.3.dist-info/top_level.txt
pypigeonhole_config-0.0.3.dist-info/RECORD
