Metadata-Version: 2.1
Name: pypigeonhole-config
Version: 0.0.3
Summary: Python YAML based Configuration
Home-page: https://github.com/psilons/pypigeonhole-config
Author: psilons
Author-email: psilons.quanta@gmail.com
License: MIT
Platform: UNKNOWN
Requires-Python: >=3.6
Requires-Dist: pycryptodome (==3.9.8)
Requires-Dist: pyyaml (==5.3.1)
Requires-Dist: pypigeonhole-simple-utils
